src/clock/andig_clock.v
module andig_clock (
  input wire in_clk,
  input wire rst,
  output reg out_clk1,
  output reg out_clk2,
  output wire out_clk2B,
  output reg out_clk_cic
);
  reg [2:0] counter;
  assign out_clk2B = ~out_clk2;
  always @(posedge in_clk or negedge rst) begin
    if (!rst) begin
      counter <= 3'b0;
      out_clk1 <= 1'b1;
      out_clk2 <= 1'b0;
      out_clk_cic <= 1'b0;
    end else begin
      if (counter <= 3'b001) begin
        out_clk1 <= 1'b1;
        out_clk2 <= 1'b0;
        out_clk_cic <= 1'b0;
        counter <= counter + 3'b1;
      end else if (counter == 3'b010) begin
        out_clk1 <= 1'b0;
        out_clk2 <= 1'b0;
        out_clk_cic <= 1'b0;
        counter <= counter + 3'b1;
      end else if (counter == 3'b011 || counter == 3'b100) begin
        out_clk1 <= 1'b0;
        out_clk2 <= 1'b1;
        out_clk_cic <= 1'b1;
        counter <= counter + 3'b1;
      end else if (counter == 3'b101) begin
        out_clk1 <= 1'b0;
        out_clk2 <= 1'b0;
        out_clk_cic <= 1'b1;
        counter <= 3'b0;
      end else begin
        counter <= 3'b0;
      end
    end
  end
endmodule

src/clock/tb_andig_clock.v
`timescale 1ns / 1ps

module tb_andig_clock;

  // 1. Deklarasi Sinyal Testbench
  reg  in_clk;
  reg  rst;
  wire out_clk1;
  wire out_clk2;
  wire out_clk2B;
  wire out_clk_cic;

  // 2. Instansiasi Unit Under Test (UUT)
  andig_clock uut (
    .in_clk(in_clk),
    .rst(rst),
    .out_clk1(out_clk1),
    .out_clk2(out_clk2),
    .out_clk2B(out_clk2B),
    .out_clk_cic(out_clk_cic)
  );

  // 3. Pembangkit Clock Utama (in_clk = 10 MHz -> Periode = 100ns)
  always begin
    #50 in_clk = ~in_clk;
  end

  // 4. Prosedur Stimulus dan Penulisan VCD
  initial begin
    // Inisialisasi Sinyal
    in_clk = 0;
    rst    = 0;

    // Membuka File VCD untuk Visualisasi di GTKWave
    $dumpfile("tb_andig_clock.vcd");
    $dumpvars(0, tb_andig_clock);

    // Tampilkan log di terminal saat ada perubahan sinyal
    $monitor("Time=%0t ns | rst=%b | counter=%d | clk1=%b | clk2=%b | clk2B=%b | clk_cic=%b",
             $time, rst, uut.counter, out_clk1, out_clk2, out_clk2B, out_clk_cic);

    // Tahan Reset selama 150 ns (Active-LOW Reset)
    #150;
    rst = 1; // Lepas Reset

    // Jalankan simulasi selama beberapa siklus penuh (misal: 2000 ns)
    #2000;

    // Selesaikan Simulasi
    $display("Simulasi Selesai!");
    $finish;
  end

endmodule

src/clock/tb_andig_clock.vcd
$date
	Tue Jul 28 11:50:34 2026
$end
$version
	Icarus Verilog
$end
$timescale
	1ps
$end
$scope module tb_andig_clock $end
$var wire 1 ! out_clk_cic $end
$var wire 1 " out_clk2B $end
$var wire 1 # out_clk2 $end
$var wire 1 $ out_clk1 $end
$var reg 1 % in_clk $end
$var reg 1 & rst $end
$scope module uut $end
$var wire 1 % in_clk $end
$var wire 1 " out_clk2B $end
$var wire 1 & rst $end
$var reg 3 ' counter [2:0] $end
$var reg 1 $ out_clk1 $end
$var reg 1 # out_clk2 $end
$var reg 1 ! out_clk_cic $end
$upscope $end
$upscope $end
$enddefinitions $end
$comment Show the parameter values. $end
$dumpall
$end
#0
$dumpvars
b0 '
0&
0%
1$
0#
1"
0!
$end
#50000
1%
#100000
0%
#150000
b1 '
1%
1&
#200000
0%
#250000
b10 '
1%
#300000
0%
#350000
b11 '
0$
1%
#400000
0%
#450000
0"
b100 '
1!
1#
1%
#500000
0%
#550000
b101 '
1%
#600000
0%
#650000
1"
b0 '
0#
1%
#700000
0%
#750000
b1 '
0!
1$
1%
#800000
0%
#850000
b10 '
1%
#900000
0%
#950000
b11 '
0$
1%
#1000000
0%
#1050000
0"
b100 '
1!
1#
1%
#1100000
0%
#1150000
b101 '
1%
#1200000
0%
#1250000
1"
b0 '
0#
1%
#1300000
0%
#1350000
b1 '
0!
1$
1%
#1400000
0%
#1450000
b10 '
1%
#1500000
0%
#1550000
b11 '
0$
1%
#1600000
0%
#1650000
0"
b100 '
1!
1#
1%
#1700000
0%
#1750000
b101 '
1%
#1800000
0%
#1850000
1"
b0 '
0#
1%
#1900000
0%
#1950000
b1 '
0!
1$
1%
#2000000
0%
#2050000
b10 '
1%
#2100000
0%
#2150000
b11 '
0$
1%
